odoo/addons/impact_data_registry/README.rst
odoo/addons/impact_data_registry/__init__.py
odoo/addons/impact_data_registry/__manifest__.py
odoo/addons/impact_data_registry/hooks.py
odoo/addons/impact_data_registry/i18n/es.po
odoo/addons/impact_data_registry/i18n/es_CA.po
odoo/addons/impact_data_registry/models/__init__.py
odoo/addons/impact_data_registry/models/impact_data_category.py
odoo/addons/impact_data_registry/models/impact_data_entry.py
odoo/addons/impact_data_registry/models/impact_data_type.py
odoo/addons/impact_data_registry/security/ir.model.access.csv
odoo/addons/impact_data_registry/static/description/icon.png
odoo/addons/impact_data_registry/tests/__init__.py
odoo/addons/impact_data_registry/tests/test_impact_data_category.py
odoo/addons/impact_data_registry/tests/test_impact_data_entry.py
odoo/addons/impact_data_registry/tests/test_impact_data_type.py
odoo/addons/impact_data_registry/views/impact_data_category_views.xml
odoo/addons/impact_data_registry/views/impact_data_entry_views.xml
odoo/addons/impact_data_registry/views/impact_data_menuitems.xml
odoo/addons/impact_data_registry/views/impact_data_type_uom_views.xml
odoo/addons/impact_data_registry/views/impact_data_type_views.xml
odoo_addon_impact_data_registry-16.0.1.1.0.dist-info/METADATA
odoo_addon_impact_data_registry-16.0.1.1.0.dist-info/WHEEL
odoo_addon_impact_data_registry-16.0.1.1.0.dist-info/top_level.txt
odoo_addon_impact_data_registry-16.0.1.1.0.dist-info/RECORD
