Metadata-Version: 2.1
Name: odoo-addon-impact-data-registry
Version: 16.0.1.1.0
Summary: Odoo Addon Impact Data Registry
Home-page: https://gitlab.com/somitcoop/projects/odoo-finanzas-eticas-addons.git
Author: Som It Cooperatiu SCCL
License: AGPL-3
Classifier: Programming Language :: Python
Classifier: Framework :: Odoo
Classifier: Framework :: Odoo :: 16.0
Classifier: License :: OSI Approved :: GNU Affero General Public License v3
Requires-Python: >=3.10
Requires-Dist: odoo<16.1dev,>=16.0a
